flask_airbrake.py
Flask_Airbrake-0.0.3.dist-info/DESCRIPTION.rst
Flask_Airbrake-0.0.3.dist-info/METADATA
Flask_Airbrake-0.0.3.dist-info/RECORD
Flask_Airbrake-0.0.3.dist-info/WHEEL
Flask_Airbrake-0.0.3.dist-info/metadata.json
Flask_Airbrake-0.0.3.dist-info/top_level.txt
