Metadata-Version: 2.0
Name: Flask-Airbrake
Version: 0.0.3
Summary: Flask extension for Airbrake
Home-page: https://github.com/rstit/flask-airbrake
Author: RST-IT
Author-email: piotr.poteralski@rst-it.com
License: BSD
Download-URL: https://github.com/rstit/flask-airbrake/tarball/0.0.3
Platform: UNKNOWN
Classifier: Development Status :: 3 - Alpha
Classifier: Intended Audience :: Developers
Classifier: Programming Language :: Python :: 3
Requires-Dist: Flask
Requires-Dist: airbrake
